ess/__init__.py
ess/ess.py
myess-1.0.0.dist-info/METADATA
myess-1.0.0.dist-info/WHEEL
myess-1.0.0.dist-info/entry_points.txt
myess-1.0.0.dist-info/top_level.txt
myess-1.0.0.dist-info/RECORD
